eurotunnel_datamodel/__init__.py
eurotunnel_datamodel/DatabaseHelpers.py
eurotunnel_datamodel/DataModel.py
eurotunnel_datamodel-0.1.4.dist-info/METADATA
eurotunnel_datamodel-0.1.4.dist-info/WHEEL
eurotunnel_datamodel-0.1.4.dist-info/RECORD
